[
  {
    "filename": "2026-03-24-233204.md",
    "title": "島嶼私語：傍晚時分，我坐在民宿的矮牆上，",
    "date": "2026-03-24T23:32:04",
    "tags": [
      "澎湖 灣 行旅",
      "嘉義 到 澎湖 船 票",
      "澎湖 晚餐",
      "澎湖 自由 行",
      "澎湖 輪 航班",
      "澎湖 日報",
      "澎湖 民宿 推薦",
      "澎湖 電影院",
      "布袋 坐 船 到 澎湖 要 多久"
    ]
  },
  {
    "filename": "2026-03-24-213203.md",
    "title": "島嶼私語：島的呼吸，有時是等待",
    "date": "2026-03-24T21:32:03",
    "tags": [
      "澎湖 電影院",
      "布袋 坐 船 到 澎湖 要 多久",
      "嘉義 到 澎湖 船 票",
      "澎湖 監理 站",
      "澎湖 最新 飯店"
    ]
  },
  {
    "filename": "2026-03-24-203201.md",
    "title": "島嶼私語：晨光從海灣那頭漫過來時，我正翻",
    "date": "2026-03-24T20:32:01",
    "tags": [
      "澎湖 灣 行旅",
      "布袋 坐 船 到 澎湖 要 多久",
      "三軍 總 醫院 澎湖 分院",
      "澎湖 日報",
      "嘉義 到 澎湖 船 票",
      "澎湖 監理 站",
      "澎湖 船 票 訂購",
      "澎湖 海戰"
    ]
  },
  {
    "filename": "2026-03-24-193158.md",
    "title": "島嶼私語：傍晚時分，我沿著灣畔的行旅小徑",
    "date": "2026-03-24T19:31:58",
    "tags": [
      "澎湖 灣 行旅",
      "澎湖 電影院",
      "澎湖 晚餐",
      "澎湖 必 去 景點",
      "嘉義 到 澎湖 船 票",
      "三軍 總 醫院 澎湖 分院",
      "澎湖 日報"
    ]
  },
  {
    "filename": "2026-03-24-183200.md",
    "title": "島嶼私語：傍晚時分，我沿著港邊散步，看著",
    "date": "2026-03-24T18:32:00",
    "tags": [
      "澎湖 地方 法院",
      "澎湖 晚餐",
      "澎湖 灣 行旅",
      "澎湖 住宿 推薦",
      "嘉義 到 澎湖 船 票",
      "澎湖 免稅 店",
      "澎湖 自由 行",
      "澎湖 民宿 推薦"
    ]
  },
  {
    "filename": "2026-03-24-173203.md",
    "title": "島嶼私語：傍晚時分，我沿著港灣散步，手裡",
    "date": "2026-03-24T17:32:03",
    "tags": [
      "澎湖 灣 行旅",
      "澎湖 晚餐",
      "澎湖 日報",
      "嘉義 到 澎湖 船 票",
      "澎湖 自由 行",
      "澎湖 最新 飯店"
    ]
  },
  {
    "filename": "2026-03-24-143204.md",
    "title": "島嶼私語：晚餐時分，我坐在民宿的矮牆上，",
    "date": "2026-03-24T14:32:04",
    "tags": [
      "澎湖 晚餐",
      "澎湖 監獄",
      "嘉義 到 澎湖 船 票",
      "澎湖 民宿 推薦",
      "澎湖 英文"
    ]
  },
  {
    "filename": "2026-03-24-133157.md",
    "title": "島嶼私語：晚餐的氣味是從巷口飄來的，帶著",
    "date": "2026-03-24T13:31:57",
    "tags": [
      "澎湖 晚餐",
      "澎湖 監獄",
      "嘉義 到 澎湖 船 票",
      "澎湖 民宿 推薦",
      "澎湖 英文"
    ]
  },
  {
    "filename": "2026-03-24-123206.md",
    "title": "島嶼私語：潮水退得遠了，露出大片大片的潮",
    "date": "2026-03-24T12:32:06",
    "tags": [
      "海 慶 澎湖 海鮮",
      "澎湖 潮汐 表",
      "澎湖 日報",
      "澎湖 監獄",
      "澎湖 怎麼 玩",
      "澎湖 晚餐",
      "澎湖 必 去 景點",
      "澎湖 灣 行旅",
      "澎湖 輪 航行 時間",
      "澎湖 海洋 渡 假 村"
    ]
  },
  {
    "filename": "2026-03-24-113153.md",
    "title": "島嶼私語：船笛聲是島嶼的呼吸",
    "date": "2026-03-24T11:31:53",
    "tags": [
      "澎湖 輪 航班",
      "澎湖 監獄",
      "澎湖 輪 航行 時間",
      "澎湖 公車",
      "澎湖 民宿 推薦",
      "澎湖 花火 節 2026 時間",
      "澎湖 住宿 推薦",
      "澎湖 輪 時間"
    ]
  },
  {
    "filename": "2026-03-24-103200.md",
    "title": "島嶼私語：潮水退去時，緝馬灣的礁岩露出黝",
    "date": "2026-03-24T10:32:00",
    "tags": [
      "緝 馬 灣 澎湖 海產",
      "布袋 坐 船 到 澎湖 要 多久",
      "澎湖 海戰",
      "澎湖 監理 站",
      "澎湖 租車 推薦",
      "澎湖 晚餐",
      "澎湖 輪 航班",
      "澎湖 監獄",
      "澎湖 輪 航行 時間"
    ]
  },
  {
    "filename": "2026-03-24-093156.md",
    "title": "島嶼私語：風從海峽那頭吹來，帶著鹽粒與時",
    "date": "2026-03-24T09:31:56",
    "tags": [
      "澎湖 海戰",
      "布袋 坐 船 到 澎湖 要 多久",
      "澎湖 輪 航班",
      "澎湖 特產",
      "台中 到 澎湖 機票",
      "澎湖 水上 活動",
      "澎湖 輪 時間",
      "澎湖 監獄"
    ]
  },
  {
    "filename": "2026-03-24-083158.md",
    "title": "島嶼私語：氣溫降下來了",
    "date": "2026-03-24T08:31:58",
    "tags": [
      "澎湖 氣溫",
      "布袋 坐 船 到 澎湖 要 多久",
      "三 總 澎湖 分院",
      "澎湖 海戰",
      "澎湖 花枝 丸",
      "澎湖 晚餐",
      "澎湖 社區 大學",
      "澎湖 花火 節 日期",
      "泳 渡 澎湖 灣 2026"
    ]
  },
  {
    "filename": "2026-03-24-082848.md",
    "title": "島嶼私語：海，是這裡永恆的呼吸",
    "date": "2026-03-24T08:28:48",
    "tags": [
      "海 慶 澎湖 海鮮",
      "布袋 坐 船 到 澎湖 要 多久",
      "澎湖 海戰",
      "澎湖 輪 航班",
      "台中 到 澎湖 機票",
      "澎湖 花枝 丸",
      "澎湖 輪 航行 時間",
      "澎湖 花火 節 日期",
      "台南 飛 澎湖",
      "泳 渡 澎湖 灣 2026"
    ]
  },
  {
    "filename": "2026-03-24-081351.md",
    "title": "島嶼私語：風從海峽那頭吹來，帶著鹽粒與時",
    "date": "2026-03-24T08:13:51",
    "tags": [
      "島嶼私語",
      "澎湖散文"
    ]
  },
  {
    "filename": "2026-03-24-073516.md",
    "title": "島嶼私語：潮水退去的時候，我總會想起那些",
    "date": "2026-03-24T07:35:16",
    "tags": [
      "島嶼私語",
      "澎湖散文"
    ]
  },
  {
    "filename": "2026-03-24-071357.md",
    "title": "島嶼私語：船在海上搖晃的時候，時間就失去",
    "date": "2026-03-24T07:13:57",
    "tags": [
      "島嶼私語",
      "澎湖散文"
    ]
  },
  {
    "filename": "2026-03-24-061747.md",
    "title": "島嶼私語：潮水退去的時候，我總會想起那些",
    "date": "2026-03-24T06:17:47",
    "tags": [
      "島嶼私語",
      "澎湖散文"
    ]
  },
  {
    "filename": "2026-03-24-061355.md",
    "title": "島嶼私語：船在海上搖晃的時候，時間會變得",
    "date": "2026-03-24T06:13:55",
    "tags": [
      "島嶼私語",
      "澎湖散文"
    ]
  },
  {
    "filename": "2026-03-24-051542.md",
    "title": "島嶼私語：潮水退去時，我總會想起那些漂流",
    "date": "2026-03-24T05:15:42",
    "tags": [
      "島嶼私語",
      "澎湖散文"
    ]
  },
  {
    "filename": "2026-03-24-051348.md",
    "title": "島嶼私語：島的呼吸，有時是緩慢的",
    "date": "2026-03-24T05:13:48",
    "tags": [
      "島嶼私語",
      "澎湖散文"
    ]
  },
  {
    "filename": "2026-03-24-043520.md",
    "title": "島嶼私語：潮水退去時，我總覺得島嶼在呼吸",
    "date": "2026-03-24T04:35:20",
    "tags": [
      "島嶼私語",
      "澎湖散文"
    ]
  },
  {
    "filename": "2026-03-24-013512.md",
    "title": "島嶼私語：租來的汽車沿著201縣道緩緩前",
    "date": "2026-03-24T01:35:12",
    "tags": [
      "島嶼私語",
      "澎湖散文"
    ]
  },
  {
    "filename": "2026-03-24-003511.md",
    "title": "島嶼私語：潮水退去後，我沿著社區大學外那",
    "date": "2026-03-24T00:35:11",
    "tags": [
      "島嶼私語",
      "澎湖散文"
    ]
  },
  {
    "filename": "2026-03-23-234731.md",
    "title": "島嶼私語：潮水退去後，沙灘上留下幾道深深",
    "date": "2026-03-23T23:47:31",
    "tags": [
      "島嶼私語",
      "澎湖散文"
    ]
  },
  {
    "filename": "2026-03-23-223513.md",
    "title": "島嶼私語：島嶼的日常，總是以各種方式滲進",
    "date": "2026-03-23T22:35:13",
    "tags": [
      "島嶼私語",
      "澎湖散文"
    ]
  },
  {
    "filename": "2026-03-23-202334.md",
    "title": "島嶼私語：島的呼吸，有時是鹹的，有時是鐵",
    "date": "2026-03-23T20:23:34",
    "tags": [
      "島嶼私語",
      "澎湖散文"
    ]
  },
  {
    "filename": "2026-03-23-134329.md",
    "title": "島嶼私語：午後的風裡有鹽的顆粒感",
    "date": "2026-03-23T13:43:29",
    "tags": [
      "島嶼私語",
      "澎湖散文"
    ]
  },
  {
    "filename": "2026-03-23-123417.md",
    "title": "島嶼私語：清晨五點半，我站在馬公港邊，看",
    "date": "2026-03-23T12:34:17",
    "tags": [
      "島嶼私語",
      "澎湖散文"
    ]
  },
  {
    "filename": "2026-03-23-114410.md",
    "title": "島嶼私語：島的呼吸，總帶著鹽分的重量",
    "date": "2026-03-23T11:44:10",
    "tags": [
      "島嶼私語",
      "澎湖散文"
    ]
  },
  {
    "filename": "2026-03-23-113410.md",
    "title": "島嶼私語：風從海峽那端吹來，帶著鹽粒與遠",
    "date": "2026-03-23T11:34:10",
    "tags": [
      "島嶼私語",
      "澎湖散文"
    ]
  },
  {
    "filename": "2026-03-23-111308.md",
    "title": "島嶼私語：風從海峽那頭吹來，帶著鹽粒與遠",
    "date": "2026-03-23T11:13:08",
    "tags": [
      "島嶼私語",
      "澎湖散文"
    ]
  },
  {
    "filename": "2026-03-23-110410.md",
    "title": "島嶼私語：海，是這裡最尋常的呼吸",
    "date": "2026-03-23T11:04:10",
    "tags": [
      "島嶼私語",
      "澎湖散文"
    ]
  },
  {
    "filename": "2026-03-23-105412.md",
    "title": "島嶼私語：晨光從《澎湖日報》的邊角漫開，",
    "date": "2026-03-23T10:54:12",
    "tags": [
      "島嶼私語",
      "澎湖散文"
    ]
  },
  {
    "filename": "2026-03-23-104415.md",
    "title": "島嶼私語：風從海峽那頭吹來，帶著鹽的質地",
    "date": "2026-03-23T10:44:15",
    "tags": [
      "島嶼私語",
      "澎湖散文"
    ]
  },
  {
    "filename": "2026-03-23-101408.md",
    "title": "島嶼私語：這一週的天氣，像極了島嶼反覆的",
    "date": "2026-03-23T10:14:08",
    "tags": [
      "島嶼私語",
      "澎湖散文"
    ]
  },
  {
    "filename": "2026-03-23-100403.md",
    "title": "島嶼私語：這一週的天氣，像極了島嶼的脾氣",
    "date": "2026-03-23T10:04:03",
    "tags": [
      "島嶼私語",
      "澎湖散文"
    ]
  },
  {
    "filename": "2026-03-23-093405.md",
    "title": "島嶼私語：風從海峽那頭吹來，帶著鹽粒與問",
    "date": "2026-03-23T09:34:05",
    "tags": [
      "島嶼私語",
      "澎湖散文"
    ]
  },
  {
    "filename": "2026-03-23-092405.md",
    "title": "島嶼私語：風從海峽那端吹來，帶著潮濕的、",
    "date": "2026-03-23T09:24:05",
    "tags": [
      "島嶼私語",
      "澎湖散文"
    ]
  },
  {
    "filename": "2026-03-23-091403.md",
    "title": "島嶼私語：風從海峽那端吹來，帶來一種微妙",
    "date": "2026-03-23T09:14:03",
    "tags": [
      "島嶼私語",
      "澎湖散文"
    ]
  },
  {
    "filename": "2026-03-23-085401.md",
    "title": "島嶼私語：風從觀音亭的海面吹來，帶著鹹味",
    "date": "2026-03-23T08:54:01",
    "tags": [
      "島嶼私語",
      "澎湖散文"
    ]
  },
  {
    "filename": "2026-03-23-083357.md",
    "title": "島嶼私語：午後，我沿著菜園的土埂走，絲瓜",
    "date": "2026-03-23T08:33:57",
    "tags": [
      "島嶼私語",
      "澎湖散文"
    ]
  },
  {
    "filename": "2026-03-23-081358.md",
    "title": "島嶼私語：風從海峽那頭吹來，帶著鹽粒與某",
    "date": "2026-03-23T08:13:58",
    "tags": [
      "島嶼私語",
      "澎湖散文"
    ]
  },
  {
    "filename": "2026-03-23-075823.md",
    "title": "島嶼私語：這座島嶼的呼吸，總是帶著鹹味與",
    "date": "2026-03-23T07:58:23",
    "tags": [
      "島嶼私語",
      "澎湖散文"
    ]
  },
  {
    "filename": "2026-03-23-074357.md",
    "title": "島嶼私語：風的季節又來了",
    "date": "2026-03-23T07:43:57",
    "tags": [
      "島嶼私語",
      "澎湖散文"
    ]
  },
  {
    "filename": "2026-03-23-071356.md",
    "title": "島嶼私語：午後，我騎著機車繞過科技大學外",
    "date": "2026-03-23T07:13:56",
    "tags": [
      "島嶼私語",
      "澎湖散文"
    ]
  },
  {
    "filename": "2026-03-23-070351.md",
    "title": "島嶼私語：租來的汽車在二零四縣道上奔馳，",
    "date": "2026-03-23T07:03:51",
    "tags": [
      "島嶼私語",
      "澎湖散文"
    ]
  },
  {
    "filename": "2026-03-23-065348.md",
    "title": "島嶼私語：風從海峽那端吹來，帶著鹹澀的訊",
    "date": "2026-03-23T06:53:48",
    "tags": [
      "島嶼私語",
      "澎湖散文"
    ]
  },
  {
    "filename": "2026-03-23-065001.md",
    "title": "島嶼私語：租車行的老闆把鑰匙遞給我時，風",
    "date": "2026-03-23T06:50:01",
    "tags": [
      "島嶼私語",
      "澎湖散文"
    ]
  },
  {
    "filename": "2026-03-23-062350.md",
    "title": "島嶼私語：日子在島上，總是以一種緩慢的、",
    "date": "2026-03-23T06:23:50",
    "tags": [
      "島嶼私語",
      "澎湖散文"
    ]
  },
  {
    "filename": "2026-03-23-061346.md",
    "title": "島嶼私語：輪的航行，是另一種時間的刻度",
    "date": "2026-03-23T06:13:46",
    "tags": [
      "島嶼私語",
      "澎湖散文"
    ]
  },
  {
    "filename": "2026-03-23-055348.md",
    "title": "島嶼私語：推開窗，海風裡混著一絲潮濕的土",
    "date": "2026-03-23T05:53:48",
    "tags": [
      "島嶼私語",
      "澎湖散文"
    ]
  },
  {
    "filename": "2026-03-23-054349.md",
    "title": "島嶼私語：風從海峽那頭吹來，帶著高雄港的",
    "date": "2026-03-23T05:43:49",
    "tags": [
      "島嶼私語",
      "澎湖散文"
    ]
  },
  {
    "filename": "2026-03-23-053345.md",
    "title": "島嶼私語：風從海峽那頭吹來，帶著一種熟悉",
    "date": "2026-03-23T05:33:45",
    "tags": [
      "島嶼私語",
      "澎湖散文"
    ]
  },
  {
    "filename": "2026-03-23-052445.md",
    "title": "島嶼私語：這一週的天氣預報，我反覆看了十",
    "date": "2026-03-23T05:24:45",
    "tags": [
      "島嶼私語",
      "澎湖散文"
    ]
  },
  {
    "filename": "2026-03-23-052313.md",
    "title": "島嶼私語：時間在這裡，是另一種航行",
    "date": "2026-03-23T05:23:13",
    "tags": [
      "島嶼私語",
      "澎湖散文"
    ]
  },
  {
    "filename": "2026-03-23-051316.md",
    "title": "島嶼私語：我總覺得，島嶼的呼吸，是從一張",
    "date": "2026-03-23T05:13:16",
    "tags": [
      "島嶼私語",
      "澎湖散文"
    ]
  },
  {
    "filename": "2026-03-23-034000.md",
    "title": "島嶼私語：風從海峽那頭吹來，帶著鹽粒與某",
    "date": "2026-03-23T03:40:00",
    "tags": [
      "島嶼私語",
      "澎湖散文"
    ]
  },
  {
    "filename": "2026-03-23-011158.md",
    "title": "島嶼私語：風從海峽那頭吹來，帶著一種熟悉",
    "date": "2026-03-23T01:11:58",
    "tags": [
      "島嶼私語",
      "澎湖散文"
    ]
  },
  {
    "filename": "2026-03-23-002501.md",
    "title": "島嶼私語：午後的風裡有鹽的氣味，我坐在民",
    "date": "2026-03-23T00:25:01",
    "tags": [
      "島嶼私語",
      "澎湖散文"
    ]
  }
]